flask_docker.py
Flask_Docker-0.2.0.dist-info/DESCRIPTION.rst
Flask_Docker-0.2.0.dist-info/METADATA
Flask_Docker-0.2.0.dist-info/metadata.json
Flask_Docker-0.2.0.dist-info/RECORD
Flask_Docker-0.2.0.dist-info/top_level.txt
Flask_Docker-0.2.0.dist-info/WHEEL
